MANIFEST.in
README.rst
setup.py
django_fhir.egg-info/PKG-INFO
django_fhir.egg-info/SOURCES.txt
django_fhir.egg-info/dependency_links.txt
django_fhir.egg-info/requires.txt
django_fhir.egg-info/top_level.txt
fhir/__init__.py
fhir/admin.py
fhir/models.py
fhir/urls.py
fhir/utils.py
fhir/fixtures/provider-directory-resources.json
fhir/tests/__init__.py
fhir/tests/test_create_view.py
fhir/tests/test_delete_view.py
fhir/tests/test_history_view.py
fhir/tests/test_read_view.py
fhir/tests/test_resource_and_interaction_support.py
fhir/tests/test_search_view.py
fhir/tests/test_update_view.py
fhir/views/__init__.py
fhir/views/create.py
fhir/views/delete.py
fhir/views/hello.py
fhir/views/history.py
fhir/views/oauth.py
fhir/views/read.py
fhir/views/rud.py
fhir/views/search.py
fhir/views/update.py
fhir/views/utils.py
fhir_io_mongo/__init__.py