Metadata-Version: 1.1
Name: django-fhir
Version: 0.0.0.5
Summary: A FHIR Server as a reusable Django application
Home-page: https://github.com/videntity/django-fhir
Author: Alan Viars (contributions - Mark Scrimshire)
Author-email: sales@videntity.com
License: GPL2
Download-URL: https://gitbub.com/videntity/django-fhir/tarball/master
Platform: UNKNOWN
Classifier: Environment :: Web Environment
Classifier: Framework :: Django
Classifier: Intended Audience :: Developers
Classifier: Operating System :: OS Independent
Classifier: Programming Language :: Python
Classifier: Programming Language :: Python :: 2.7
Classifier: Topic :: Internet :: WWW/HTTP
Classifier: Topic :: Internet :: WWW/HTTP :: Dynamic Content
